vote/__init__.py
vote/admin.py
vote/apps.py
vote/managers.py
vote/models.py
vote/tests.py
vote/utils.py
vote/views.py
vote/migrations/0001_initial.py
vote/migrations/0002_auto_20161229_1022.py
vote/migrations/0003_vote_action.py
vote/migrations/0004_auto_20170110_1150.py
vote/migrations/__init__.py
vote/signals/__init__.py
vote/templatetags/__init__.py
vote/templatetags/vote.py
django_vote-2.4.0.dist-info/LICENSE
django_vote-2.4.0.dist-info/METADATA
django_vote-2.4.0.dist-info/WHEEL
django_vote-2.4.0.dist-info/top_level.txt
django_vote-2.4.0.dist-info/RECORD
